bgt60_py.cpython-37m-arm-linux-gnueabihf.so
radar_bgt60-1.0.0.dist-info/METADATA
radar_bgt60-1.0.0.dist-info/WHEEL
radar_bgt60-1.0.0.dist-info/top_level.txt
radar_bgt60-1.0.0.dist-info/RECORD
